HRR/__init__.py
HRR/with_flax.py
HRR/with_jax.py
HRR/with_pytorch.py
HRR/with_tensorflow.py
HRR/real/__init__.py
HRR/real/with_flax.py
HRR/real/with_jax.py
HRR/real/with_pytorch.py
HRR/real/with_tensorflow.py
hrr-1.2.3.dist-info/LICENSE
hrr-1.2.3.dist-info/METADATA
hrr-1.2.3.dist-info/WHEEL
hrr-1.2.3.dist-info/top_level.txt
hrr-1.2.3.dist-info/RECORD
