Metadata-Version: 2.1
Name: hrr
Version: 1.2.3
Summary: Holographic Reduced Representations
Home-page: UNKNOWN
Author: Mohammad Mahmudul Alam
License: MIT
Platform: UNKNOWN
Classifier: Programming Language :: Python :: 3
Classifier: Operating System :: OS Independent
Requires-Python: >=3.6
License-File: LICENSE
